heystac/__init__.py
heystac/catalog.py
heystac/check.py
heystac/cli.py
heystac/collection.py
heystac/config.py
heystac/crawl.py
heystac/item.py
heystac/link.py
heystac/node.py
heystac/rate.py
heystac/rating.py
heystac/rules.py
heystac/stac_object.py
heystac-0.0.1.dist-info/METADATA
heystac-0.0.1.dist-info/WHEEL
heystac-0.0.1.dist-info/entry_points.txt
heystac-0.0.1.dist-info/licenses/LICENSE.txt
heystac-0.0.1.dist-info/RECORD
