Metadata-Version: 2.3
Name: heystac
Version: 0.0.1
Summary: Command-line interface (CLI) to rate and crawl STAC
Author-email: Pete Gadomski <pete.gadomski@gmail.com>
License: Copyright 2024 Pete Gadomski <pete.gadomski@gmail.com>
Keywords: stac
Classifier: License :: OSI Approved :: MIT License
Classifier: Natural Language :: English
Classifier: Programming Language :: Python
Classifier: Programming Language :: Python :: 3.12
Classifier: Programming Language :: Python :: 3.13
Classifier: Topic :: Scientific/Engineering :: GIS
Requires-Python: >=3.12
Requires-Dist: click>=8.1.7
Requires-Dist: httpx>=0.27.2
Requires-Dist: jsonschema>=4.23.0
Requires-Dist: pydantic-settings>=2.6.1
Requires-Dist: pydantic>=2.9.2
Requires-Dist: pystac[validation]>=1.11.0
Requires-Dist: shapely>=2.0.6
Requires-Dist: tabulate>=0.9.0
Requires-Dist: toml>=0.10.2
Requires-Dist: tqdm>=4.67.0
